vacolba_looker_data/__init__.py
vacolba_looker_data/looker_studio/__init__.py
vacolba_looker_data/looker_studio/looker_studio.py
vacolba_looker_data/utils/__init__.py
vacolba_looker_data/utils/utils.py
vacolba_looker_data/utils/looker_studio/__init__.py
vacolba_looker_data/utils/looker_studio/methods.py
vacolba_looker_data/utils/webdriver/__init__.py
vacolba_looker_data/utils/webdriver/configurations.py
vacolba_looker_data/utils/webdriver/methods.py
get_looker_data-1.0.8.dist-info/LICENSE.txt
get_looker_data-1.0.8.dist-info/METADATA
get_looker_data-1.0.8.dist-info/WHEEL
get_looker_data-1.0.8.dist-info/entry_points.txt
get_looker_data-1.0.8.dist-info/top_level.txt
get_looker_data-1.0.8.dist-info/RECORD
