Metadata-Version: 2.1
Name: get_looker_data
Version: 1.0.8
Summary: General functions for the implementation of looker studio data.
Home-page: https://github.com/rgramos/vacolba-looker-data.git
License: GPLv3
Classifier: Programming Language :: Python :: 3
Classifier: License :: OSI Approved :: GNU General Public License v3 (GPLv3)
License-File: LICENSE.txt
